python_sqlite_log_handler/__init__.py
python_sqlite_log_handler-1.0.0.dist-info/licenses/LICENSE.txt
python_sqlite_log_handler-1.0.0.dist-info/METADATA
python_sqlite_log_handler-1.0.0.dist-info/WHEEL
python_sqlite_log_handler-1.0.0.dist-info/top_level.txt
python_sqlite_log_handler-1.0.0.dist-info/RECORD
