Metadata-Version: 2.4
Name: python_sqlite_log_handler
Version: 1.0.0
Summary: SQLite log handler for Python logging module
Home-page: https://github.com/rogervila/python_sqlite_log_handler
Download-URL: https://github.com/rogervila/python_sqlite_log_handler/archive/1.0.0.tar.gz
Author: Roger Vilà
Author-email: rogervila@me.com
License: MIT
Keywords: sqlite,logging,handler
Classifier: Development Status :: 5 - Production/Stable
Classifier: Intended Audience :: Developers
Classifier: Topic :: Software Development :: Build Tools
Classifier: License :: OSI Approved :: MIT License
Classifier: Programming Language :: Python :: 3.12
License-File: LICENSE.txt
Dynamic: author
Dynamic: author-email
Dynamic: classifier
Dynamic: description
Dynamic: description-content-type
Dynamic: download-url
Dynamic: home-page
Dynamic: keywords
Dynamic: license
Dynamic: license-file
Dynamic: summary
